odoo/addons/community_maps_key_submissions/__init__.py
odoo/addons/community_maps_key_submissions/__manifest__.py
odoo/addons/community_maps_key_submissions/models/__init__.py
odoo/addons/community_maps_key_submissions/models/cm_crowdfunding_notification_request.py
odoo/addons/community_maps_key_submissions/models/cm_form_submission.py
odoo/addons/community_maps_key_submissions/models/cm_map.py
odoo/addons/community_maps_key_submissions/models/cm_place.py
odoo/addons/community_maps_key_submissions/security/ir.model.access.csv
odoo/addons/community_maps_key_submissions/views/cm_form_submission.xml
odoo/addons/community_maps_key_submissions/views/cm_map.xml
odoo/addons/community_maps_key_submissions/views/cm_place.xml
odoo_addon_community_maps_key_submissions-16.0.1.0.1.1.dist-info/METADATA
odoo_addon_community_maps_key_submissions-16.0.1.0.1.1.dist-info/WHEEL
odoo_addon_community_maps_key_submissions-16.0.1.0.1.1.dist-info/top_level.txt
odoo_addon_community_maps_key_submissions-16.0.1.0.1.1.dist-info/RECORD
