Metadata-Version: 2.1
Name: odoo-addon-community_maps_key_submissions
Version: 16.0.1.0.1.1
Requires-Python: >=3.10
Requires-Dist: odoo-addon-community_maps>=16.0dev,<16.1dev
Requires-Dist: odoo>=16.0a,<16.1dev
Summary: Define some submissions on the map as key submissions
Home-page: https://gitlab.com/somitcoop/erp-research/community-maps
Author: Community maps
Classifier: Programming Language :: Python
Classifier: Framework :: Odoo
Classifier: Framework :: Odoo :: 16.0
